{
  "video": "/root/autodl-tmp/aiv/data/refvideo/animals_and_ecology/animals_and_ecology_030_multi.mp4",
  "summary": {
    "items": 10,
    "enter_bank": 8,
    "clip_range_sec": [
      0.0,
      14.43
    ],
    "mode": "multi-turn"
  },
  "items": [
    {
      "id": "v1",
      "type": "VQA",
      "name": "Does the buffalo in the background stay stationary without moving?",
      "signals": [
        "balance(oX)",
        "support(oA,oB)",
        "continuity(oX)",
        "friction_sliding(oA,on:oB)"
      ],
      "content_score_60": 30,
      "signal_score_40": 40.0,
      "total_score_100": 70.0,
      "duplicate_penalized": false,
      "signal_detail": {
        "continuity(oX)": 36.6667,
        "balance(oX)": 7.1667,
        "support(oA,oB)": 7.0,
        "friction_sliding(oA,on:oB)": 6.0
      },
      "content_score_raw": "30"
    },
    {
      "id": "v2",
      "type": "VQA",
      "name": "Does the lion lean on the log while maintaining balance?",
      "signals": [
        "biological_motion(buffalo)",
        "prohibited_intersection(buffalo,lion)"
      ],
      "content_score_60": 50,
      "signal_score_40": 40.0,
      "total_score_100": 90.0,
      "duplicate_penalized": false,
      "signal_detail": {
        "biological_motion(buffalo)": 38.3333,
        "prohibited_intersection(buffalo,lion)": 7.3333
      },
      "content_score_raw": "50"
    },
    {
      "id": "v3",
      "type": "VQA",
      "name": "Does the acacia tree provide structural support for the large branches that the lion leans on?",
      "signals": [
        "support(oA,oB)"
      ],
      "content_score_60": 40,
      "signal_score_40": 35.0,
      "total_score_100": 75.0,
      "duplicate_penalized": false,
      "signal_detail": {
        "support(oA,oB)": 35.0
      },
      "content_score_raw": "40"
    },
    {
      "id": "v4",
      "type": "VQA",
      "name": "Is the zebra present in the background throughout the clip?",
      "signals": [
        "containment(zebra,background)",
        "continuity(zebra)"
      ],
      "content_score_60": 40,
      "signal_score_40": 40.0,
      "total_score_100": 80.0,
      "duplicate_penalized": false,
      "signal_detail": {
        "continuity(zebra)": 36.6667,
        "containment(zebra,background)": 5.8333
      },
      "content_score_raw": "40"
    },
    {
      "id": "v5",
      "type": "VQA",
      "name": "Can a lion climb and balance on a tree branch as shown?",
      "signals": [
        "biological_motion(lion)",
        "support(lion,branch)",
        "balance(lion)"
      ],
      "content_score_60": 50,
      "signal_score_40": 40.0,
      "total_score_100": 90.0,
      "duplicate_penalized": false,
      "signal_detail": {
        "biological_motion(lion)": 38.3333,
        "balance(lion)": 7.1667,
        "support(lion,branch)": 7.0
      },
      "content_score_raw": "50"
    },
    {
      "id": "a1",
      "type": "assertion",
      "name": "The lion leans on the log, which is part of the acacia tree.",
      "signals": [
        "balance(oX)",
        "support(oA,oB)"
      ],
      "content_score_60": 60,
      "signal_score_40": 40.0,
      "total_score_100": 100.0,
      "duplicate_penalized": false,
      "signal_detail": {
        "balance(oX)": 35.8333,
        "support(oA,oB)": 7.0
      },
      "content_score_raw": "60"
    },
    {
      "id": "a2",
      "type": "assertion",
      "name": "The buffalo in the background remains stationary and does not interact with other objects.",
      "signals": [
        "continuity(oX)",
        "friction_sliding(oA,on:oB)"
      ],
      "content_score_60": 60,
      "signal_score_40": 40.0,
      "total_score_100": 100.0,
      "duplicate_penalized": false,
      "signal_detail": {
        "continuity(oX)": 36.6667,
        "friction_sliding(oA,on:oB)": 6.0
      },
      "content_score_raw": "60"
    },
    {
      "id": "a3",
      "type": "assertion",
      "name": "The buffalo stands still without approaching the lion non-threateningly.",
      "signals": [
        "biological_motion(buffalo)",
        "prohibited_intersection(buffalo,lion)"
      ],
      "content_score_60": 60,
      "signal_score_40": 40.0,
      "total_score_100": 100.0,
      "duplicate_penalized": false,
      "signal_detail": {
        "biological_motion(buffalo)": 38.3333,
        "prohibited_intersection(buffalo,lion)": 7.3333
      },
      "content_score_raw": "60"
    },
    {
      "id": "a4",
      "type": "assertion",
      "name": "Zebras are visible in the background throughout the video.",
      "signals": [
        "containment(zebra,background)",
        "continuity(zebra)"
      ],
      "content_score_60": 60,
      "signal_score_40": 40.0,
      "total_score_100": 100.0,
      "duplicate_penalized": false,
      "signal_detail": {
        "continuity(zebra)": 36.6667,
        "containment(zebra,background)": 5.8333
      },
      "content_score_raw": "60"
    },
    {
      "id": "a5",
      "type": "assertion",
      "name": "The lion climbs a tree using its limbs to support itself.",
      "signals": [
        "biological_motion(oA)"
      ],
      "content_score_60": 60,
      "signal_score_40": 38.33,
      "total_score_100": 98.33,
      "duplicate_penalized": false,
      "signal_detail": {
        "biological_motion(oA)": 38.3333
      },
      "content_score_raw": "60"
    }
  ],
  "bank_ids": [
    "v2",
    "v4",
    "v5",
    "a1",
    "a2",
    "a3",
    "a4",
    "a5"
  ]
}