{
  "meta": {
    "video": "/root/autodl-tmp/aiv/videodata/refvideo/landscape/landscape_086_single.mp4",
    "window_sec": 6.0,
    "hop_sec": 3.0,
    "fps_per_window": 6,
    "resize_short": 448,
    "model": "openbmb/MiniCPM-V-4_5",
    "backend": "decord",
    "dtype": "bf16",
    "min_span_sec": 0.1
  },
  "fine": {
    "entities": [
      {
        "id": "o1",
        "name": "wave",
        "attributes": {
          "signature": [
            "foam-at-the-edge-of-water"
          ]
        },
        "spans": [
          [
            0.0,
            8.7
          ]
        ]
      }
    ],
    "relations": []
  },
  "fine_windows": [
    {
      "start": 0.0,
      "end": 8.7,
      "entities": [
        {
          "id": "o1",
          "name": "wave",
          "attributes": {
            "signature": [
              "foam-at-the-edge-of-water"
            ]
          },
          "spans": [
            [
              0.0,
              8.7
            ]
          ]
        }
      ],
      "relations": []
    }
  ],
  "views": {
    "objects_count": {
      "wave": 1
    },
    "objects_count_display": {
      "wave": 1
    },
    "attributes": {
      "wave": {
        "signature": [
          "foam-at-the-edge-of-water"
        ]
      }
    },
    "triplets": []
  }
}