{
  "video": "/root/autodl-tmp/aiv/data/refvideo/landscape/landscape_056_multi.mp4",
  "summary": {
    "items": 10,
    "enter_bank": 9,
    "clip_range_sec": [
      0.0,
      18.1
    ],
    "mode": "multi-turn"
  },
  "items": [
    {
      "id": "v1",
      "type": "VQA",
      "name": "Do the cars in the background move unexpectedly?",
      "signals": [
        "rigid_transform(car)",
        "deformation(car)",
        "fracture(car)",
        "wheel_rolling(car)",
        "rigid_transform(tree)"
      ],
      "content_score_60": 5,
      "signal_score_40": 40.0,
      "total_score_100": 45.0,
      "duplicate_penalized": false,
      "signal_detail": {
        "deformation(car)": 40.0,
        "rigid_transform(car)": 7.5,
        "rigid_transform(tree)": 7.5,
        "fracture(car)": 6.3333,
        "wheel_rolling(car)": 6.0
      },
      "content_score_raw": "5"
    },
    {
      "id": "v2",
      "type": "VQA",
      "name": "Are the trees stationary throughout the clip?",
      "signals": [
        "rigid_transform(tree)",
        "rigid_transform(car)"
      ],
      "content_score_60": 40,
      "signal_score_40": 40.0,
      "total_score_100": 80.0,
      "duplicate_penalized": false,
      "signal_detail": {
        "rigid_transform(tree)": 37.5,
        "rigid_transform(car)": 7.5
      },
      "content_score_raw": "40"
    },
    {
      "id": "v3",
      "type": "VQA",
      "name": "Do the shadows on the ground match the positions of the trees and parked vehicles?",
      "signals": [
        "shadow_consistency(car)",
        "shadow_consistency(tree)",
        "rigid_transform(oX)"
      ],
      "content_score_60": 50,
      "signal_score_40": 40.0,
      "total_score_100": 90.0,
      "duplicate_penalized": false,
      "signal_detail": {
        "rigid_transform(oX)": 37.5,
        "shadow_consistency(car)": 7.3333,
        "shadow_consistency(tree)": 7.3333
      },
      "content_score_raw": "50"
    },
    {
      "id": "v4",
      "type": "VQA",
      "name": "Does the yellow sign remain attached to the tree trunk without shifting position?",
      "signals": [
        "rigid_transform(sign)",
        "continuity(sign-on-tree)"
      ],
      "content_score_60": 50,
      "signal_score_40": 40.0,
      "total_score_100": 90.0,
      "duplicate_penalized": false,
      "signal_detail": {
        "rigid_transform(sign)": 37.5,
        "continuity(sign-on-tree)": 7.3333
      },
      "content_score_raw": "50"
    },
    {
      "id": "v5",
      "type": "VQA",
      "name": "Are the tree trunks straight and not bent or broken?",
      "signals": [
        "deformation(oX)",
        "fracture(oX)"
      ],
      "content_score_60": 50,
      "signal_score_40": 40.0,
      "total_score_100": 90.0,
      "duplicate_penalized": false,
      "signal_detail": {
        "deformation(oX)": 40.0,
        "fracture(oX)": 6.3333
      },
      "content_score_raw": "50"
    },
    {
      "id": "a1",
      "type": "assertion",
      "name": "Trees and cars remain stationary in the forest scene.",
      "signals": [
        "rigid_transform(tree)",
        "rigid_transform(car)"
      ],
      "content_score_60": 50,
      "signal_score_40": 40.0,
      "total_score_100": 90.0,
      "duplicate_penalized": false,
      "signal_detail": {
        "rigid_transform(tree)": 37.5,
        "rigid_transform(car)": 7.5
      },
      "content_score_raw": "50"
    },
    {
      "id": "a2",
      "type": "assertion",
      "name": "Parked cars do not move or deform unexpectedly.",
      "signals": [
        "rigid_transform(car)",
        "deformation(car)",
        "fracture(car)",
        "wheel_rolling(car)",
        "rigid_transform(tree)"
      ],
      "content_score_60": 50,
      "signal_score_40": 40.0,
      "total_score_100": 90.0,
      "duplicate_penalized": false,
      "signal_detail": {
        "deformation(car)": 40.0,
        "rigid_transform(car)": 7.5,
        "rigid_transform(tree)": 7.5,
        "fracture(car)": 6.3333,
        "wheel_rolling(car)": 6.0
      },
      "content_score_raw": "50"
    },
    {
      "id": "a3",
      "type": "assertion",
      "name": "Shadows on the ground match the position of trees and sunlight.",
      "signals": [
        "shadow_consistency(car)",
        "shadow_consistency(tree)"
      ],
      "content_score_60": 50,
      "signal_score_40": 40.0,
      "total_score_100": 90.0,
      "duplicate_penalized": false,
      "signal_detail": {
        "shadow_consistency(car)": 36.6667,
        "shadow_consistency(tree)": 7.3333
      },
      "content_score_raw": "50"
    },
    {
      "id": "a4",
      "type": "assertion",
      "name": "The yellow sign is fixed to the tree trunk, showing no movement.",
      "signals": [
        "continuity(sign-on-tree)",
        "rigid_transform(sign)"
      ],
      "content_score_60": 50,
      "signal_score_40": 40.0,
      "total_score_100": 90.0,
      "duplicate_penalized": false,
      "signal_detail": {
        "rigid_transform(sign)": 37.5,
        "continuity(sign-on-tree)": 7.3333
      },
      "content_score_raw": "50"
    },
    {
      "id": "a5",
      "type": "assertion",
      "name": "No objects show sudden collision or interpenetration.",
      "signals": [
        "collision(oA,oB)",
        "interpenetration(oA,oB)"
      ],
      "content_score_60": 50,
      "signal_score_40": 40.0,
      "total_score_100": 90.0,
      "duplicate_penalized": false,
      "signal_detail": {
        "interpenetration(oA,oB)": 35.8333,
        "collision(oA,oB)": 6.3333
      },
      "content_score_raw": "50"
    }
  ],
  "bank_ids": [
    "v2",
    "v3",
    "v4",
    "v5",
    "a1",
    "a2",
    "a3",
    "a4",
    "a5"
  ]
}