{
  "video": "/root/autodl-tmp/aiv/data/refvideo/landscape/landscape_062_single.mp4",
  "summary": {
    "items": 10,
    "enter_bank": 9,
    "clip_range_sec": [
      0.0,
      9.37
    ],
    "mode": "multi-turn"
  },
  "items": [
    {
      "id": "v1",
      "type": "VQA",
      "name": "Does water flow downward through the rock gorge due to gravity?",
      "signals": [
        "trajectory_dir(water,axis)"
      ],
      "content_score_60": 60,
      "signal_score_40": 38.33,
      "total_score_100": 98.33,
      "duplicate_penalized": false,
      "signal_detail": {
        "trajectory_dir(water,axis)": 38.3333
      },
      "content_score_raw": "60"
    },
    {
      "id": "v2",
      "type": "VQA",
      "name": "Do snow patches remain static on the rocky surface without sudden movement?",
      "signals": [
        "continuity(snow)"
      ],
      "content_score_60": 50,
      "signal_score_40": 36.67,
      "total_score_100": 86.67,
      "duplicate_penalized": false,
      "signal_detail": {
        "continuity(snow)": 36.6667
      },
      "content_score_raw": "50"
    },
    {
      "id": "v3",
      "type": "VQA",
      "name": "Are the two streams of the waterfall consistent in their flow pattern throughout the clip?",
      "signals": [
        "continuity(waterfall)"
      ],
      "content_score_60": 55,
      "signal_score_40": 36.67,
      "total_score_100": 91.67,
      "duplicate_penalized": false,
      "signal_detail": {
        "continuity(waterfall)": 36.6667
      },
      "content_score_raw": "55"
    },
    {
      "id": "v4",
      "type": "VQA",
      "name": "Does grass vegetation stay between rocks and maintain its green color with no significant deformation?",
      "signals": [
        "deformation(grass)",
        "continuity(grass)"
      ],
      "content_score_60": 50,
      "signal_score_40": 40.0,
      "total_score_100": 90.0,
      "duplicate_penalized": false,
      "signal_detail": {
        "deformation(grass)": 40.0,
        "continuity(grass)": 7.3333
      },
      "content_score_raw": "50"
    },
    {
      "id": "v5",
      "type": "VQA",
      "name": "Do rocks retain their rough texture and brown-gray color across the video?",
      "signals": [
        "material_optics(rock)"
      ],
      "content_score_60": 55,
      "signal_score_40": 37.5,
      "total_score_100": 92.5,
      "duplicate_penalized": false,
      "signal_detail": {
        "material_optics(rock)": 37.5
      },
      "content_score_raw": "55"
    },
    {
      "id": "a1",
      "type": "assertion",
      "name": "Water flows downward through the rock gorge due to gravity.",
      "signals": [
        "trajectory_dir(water,axis)"
      ],
      "content_score_60": 60,
      "signal_score_40": 38.33,
      "total_score_100": 98.33,
      "duplicate_penalized": false,
      "signal_detail": {
        "trajectory_dir(water,axis)": 38.3333
      },
      "content_score_raw": "60"
    },
    {
      "id": "a2",
      "type": "assertion",
      "name": "Snow patches remain static on the rocky surface without movement.",
      "signals": [
        "continuity(snow)"
      ],
      "content_score_60": 30,
      "signal_score_40": 36.67,
      "total_score_100": 66.67,
      "duplicate_penalized": true,
      "signal_detail": {
        "continuity(snow)": 36.6667
      },
      "content_score_raw": "50"
    },
    {
      "id": "a3",
      "type": "assertion",
      "name": "Grass vegetation remains in place between rocks, green and undisturbed.",
      "signals": [
        "deformation(grass)",
        "continuity(grass)"
      ],
      "content_score_60": 50,
      "signal_score_40": 40.0,
      "total_score_100": 90.0,
      "duplicate_penalized": false,
      "signal_detail": {
        "deformation(grass)": 40.0,
        "continuity(grass)": 7.3333
      },
      "content_score_raw": "50"
    },
    {
      "id": "a4",
      "type": "assertion",
      "name": "The waterfall's two streams maintain consistent flow patterns throughout.",
      "signals": [
        "continuity(waterfall)"
      ],
      "content_score_60": 55,
      "signal_score_40": 36.67,
      "total_score_100": 91.67,
      "duplicate_penalized": false,
      "signal_detail": {
        "continuity(waterfall)": 36.6667
      },
      "content_score_raw": "55"
    },
    {
      "id": "a5",
      "type": "assertion",
      "name": "Rocks retain their rough texture and brown-gray color.",
      "signals": [
        "material_optics(rock)"
      ],
      "content_score_60": 55,
      "signal_score_40": 37.5,
      "total_score_100": 92.5,
      "duplicate_penalized": false,
      "signal_detail": {
        "material_optics(rock)": 37.5
      },
      "content_score_raw": "55"
    }
  ],
  "bank_ids": [
    "v1",
    "v2",
    "v3",
    "v4",
    "v5",
    "a1",
    "a3",
    "a4",
    "a5"
  ]
}